{
    "total": [
        {
            "id": "100074749290620",
            "count": 136
        },
        {
            "id": "100023416734135",
            "count": 0
        },
        {
            "id": "100027948137517",
            "count": 0
        },
        {
            "id": "100029006250818",
            "count": 0
        },
        {
            "id": "100056087464917",
            "count": 16
        },
        {
            "id": "100071067754623",
            "count": 6
        },
        {
            "id": "100061813050338",
            "count": 0
        },
        {
            "id": "100055836259425",
            "count": 9
        },
        {
            "id": "100023854140281",
            "count": 38
        },
        {
            "id": "100010665249572",
            "count": 0
        },
        {
            "id": "100020878699997",
            "count": 1
        },
        {
            "id": "100047514954366",
            "count": 35
        },
        {
            "id": "100065262047714",
            "count": 1
        },
        {
            "id": "100067243941940",
            "count": 2
        },
        {
            "id": "100067053683911",
            "count": 2
        },
        {
            "id": "100022366803401",
            "count": 0
        },
        {
            "id": "100079666113333",
            "count": 0
        },
        {
            "id": "100073535343306",
            "count": 52
        },
        {
            "id": "100011692905710",
            "count": 0
        },
        {
            "id": "100079453483299",
            "count": 53
        },
        {
            "id": "100018018068309",
            "count": 0
        },
        {
            "id": "100067031242787",
            "count": 0
        },
        {
            "id": "100066236055494",
            "count": 0
        },
        {
            "id": "100055693593723",
            "count": 0
        },
        {
            "id": "100072701712223",
            "count": 28
        },
        {
            "id": "100065030048161",
            "count": 2
        },
        {
            "id": "100009166856330",
            "count": 0
        },
        {
            "id": "100052746136998",
            "count": 5
        },
        {
            "id": "100014762199928",
            "count": 20
        },
        {
            "id": "100004216305793",
            "count": 0
        },
        {
            "id": "100048984994148",
            "count": 0
        },
        {
            "id": "100012443164409",
            "count": 1
        },
        {
            "id": "100083380423639",
            "count": 20
        },
        {
            "id": "100016663181910",
            "count": 64
        },
        {
            "id": "100059137774371",
            "count": 0
        },
        {
            "id": "100011467808949",
            "count": 25
        },
        {
            "id": "100034707022479",
            "count": 0
        },
        {
            "id": "100022702847197",
            "count": 0
        },
        {
            "id": "100003705008879",
            "count": 0
        },
        {
            "id": "100065602475816",
            "count": 0
        },
        {
            "id": "100000154104641",
            "count": 76
        },
        {
            "id": "100085875930262",
            "count": 196
        },
        {
            "id": "100062498004609",
            "count": 104
        },
        {
            "id": "100013965996688",
            "count": 6
        },
        {
            "id": "100004763292113",
            "count": 24
        },
        {
            "id": "100014483565503",
            "count": 7
        },
        {
            "id": "100060277764031",
            "count": 0
        },
        {
            "id": "100017700078094",
            "count": 1
        },
        {
            "id": "100078289572599",
            "count": 455
        },
        {
            "id": "100052712120430",
            "count": 40
        },
        {
            "id": "100039250569229",
            "count": 3
        },
        {
            "id": "100079492153938",
            "count": 21
        }
    ],
    "week": [
        {
            "id": "100074749290620",
            "count": 136
        },
        {
            "id": "100023416734135",
            "count": 0
        },
        {
            "id": "100027948137517",
            "count": 0
        },
        {
            "id": "100029006250818",
            "count": 0
        },
        {
            "id": "100056087464917",
            "count": 16
        },
        {
            "id": "100071067754623",
            "count": 6
        },
        {
            "id": "100061813050338",
            "count": 0
        },
        {
            "id": "100055836259425",
            "count": 9
        },
        {
            "id": "100023854140281",
            "count": 38
        },
        {
            "id": "100010665249572",
            "count": 0
        },
        {
            "id": "100020878699997",
            "count": 1
        },
        {
            "id": "100047514954366",
            "count": 35
        },
        {
            "id": "100065262047714",
            "count": 1
        },
        {
            "id": "100067243941940",
            "count": 2
        },
        {
            "id": "100067053683911",
            "count": 2
        },
        {
            "id": "100022366803401",
            "count": 0
        },
        {
            "id": "100079666113333",
            "count": 0
        },
        {
            "id": "100073535343306",
            "count": 52
        },
        {
            "id": "100011692905710",
            "count": 0
        },
        {
            "id": "100079453483299",
            "count": 53
        },
        {
            "id": "100018018068309",
            "count": 0
        },
        {
            "id": "100067031242787",
            "count": 0
        },
        {
            "id": "100066236055494",
            "count": 0
        },
        {
            "id": "100055693593723",
            "count": 0
        },
        {
            "id": "100072701712223",
            "count": 28
        },
        {
            "id": "100065030048161",
            "count": 2
        },
        {
            "id": "100009166856330",
            "count": 0
        },
        {
            "id": "100052746136998",
            "count": 5
        },
        {
            "id": "100014762199928",
            "count": 20
        },
        {
            "id": "100004216305793",
            "count": 0
        },
        {
            "id": "100048984994148",
            "count": 0
        },
        {
            "id": "100012443164409",
            "count": 1
        },
        {
            "id": "100083380423639",
            "count": 20
        },
        {
            "id": "100016663181910",
            "count": 64
        },
        {
            "id": "100059137774371",
            "count": 0
        },
        {
            "id": "100011467808949",
            "count": 25
        },
        {
            "id": "100034707022479",
            "count": 0
        },
        {
            "id": "100022702847197",
            "count": 0
        },
        {
            "id": "100003705008879",
            "count": 0
        },
        {
            "id": "100065602475816",
            "count": 0
        },
        {
            "id": "100000154104641",
            "count": 76
        },
        {
            "id": "100085875930262",
            "count": 196
        },
        {
            "id": "100062498004609",
            "count": 104
        },
        {
            "id": "100013965996688",
            "count": 6
        },
        {
            "id": "100004763292113",
            "count": 24
        },
        {
            "id": "100014483565503",
            "count": 7
        },
        {
            "id": "100060277764031",
            "count": 0
        },
        {
            "id": "100017700078094",
            "count": 1
        },
        {
            "id": "100078289572599",
            "count": 455
        },
        {
            "id": "100052712120430",
            "count": 40
        },
        {
            "id": "100039250569229",
            "count": 3
        },
        {
            "id": "100079492153938",
            "count": 21
        }
    ],
    "day": [
        {
            "id": "100074749290620",
            "count": 136
        },
        {
            "id": "100023416734135",
            "count": 0
        },
        {
            "id": "100027948137517",
            "count": 0
        },
        {
            "id": "100029006250818",
            "count": 0
        },
        {
            "id": "100056087464917",
            "count": 16
        },
        {
            "id": "100071067754623",
            "count": 6
        },
        {
            "id": "100061813050338",
            "count": 0
        },
        {
            "id": "100055836259425",
            "count": 9
        },
        {
            "id": "100023854140281",
            "count": 38
        },
        {
            "id": "100010665249572",
            "count": 0
        },
        {
            "id": "100020878699997",
            "count": 1
        },
        {
            "id": "100047514954366",
            "count": 35
        },
        {
            "id": "100065262047714",
            "count": 1
        },
        {
            "id": "100067243941940",
            "count": 2
        },
        {
            "id": "100067053683911",
            "count": 2
        },
        {
            "id": "100022366803401",
            "count": 0
        },
        {
            "id": "100079666113333",
            "count": 0
        },
        {
            "id": "100073535343306",
            "count": 52
        },
        {
            "id": "100011692905710",
            "count": 0
        },
        {
            "id": "100079453483299",
            "count": 53
        },
        {
            "id": "100018018068309",
            "count": 0
        },
        {
            "id": "100067031242787",
            "count": 0
        },
        {
            "id": "100066236055494",
            "count": 0
        },
        {
            "id": "100055693593723",
            "count": 0
        },
        {
            "id": "100072701712223",
            "count": 28
        },
        {
            "id": "100065030048161",
            "count": 2
        },
        {
            "id": "100009166856330",
            "count": 0
        },
        {
            "id": "100052746136998",
            "count": 5
        },
        {
            "id": "100014762199928",
            "count": 20
        },
        {
            "id": "100004216305793",
            "count": 0
        },
        {
            "id": "100048984994148",
            "count": 0
        },
        {
            "id": "100012443164409",
            "count": 1
        },
        {
            "id": "100083380423639",
            "count": 20
        },
        {
            "id": "100016663181910",
            "count": 64
        },
        {
            "id": "100059137774371",
            "count": 0
        },
        {
            "id": "100011467808949",
            "count": 25
        },
        {
            "id": "100034707022479",
            "count": 0
        },
        {
            "id": "100022702847197",
            "count": 0
        },
        {
            "id": "100003705008879",
            "count": 0
        },
        {
            "id": "100065602475816",
            "count": 0
        },
        {
            "id": "100000154104641",
            "count": 76
        },
        {
            "id": "100085875930262",
            "count": 196
        },
        {
            "id": "100062498004609",
            "count": 104
        },
        {
            "id": "100013965996688",
            "count": 6
        },
        {
            "id": "100004763292113",
            "count": 24
        },
        {
            "id": "100014483565503",
            "count": 7
        },
        {
            "id": "100060277764031",
            "count": 0
        },
        {
            "id": "100017700078094",
            "count": 1
        },
        {
            "id": "100078289572599",
            "count": 455
        },
        {
            "id": "100052712120430",
            "count": 40
        },
        {
            "id": "100039250569229",
            "count": 3
        },
        {
            "id": "100079492153938",
            "count": 21
        }
    ],
    "time": 2,
    "last": {
        "time": 6,
        "day": [
            {
                "id": "100074749290620",
                "count": 0
            },
            {
                "id": "100023416734135",
                "count": 0
            },
            {
                "id": "100027948137517",
                "count": 0
            },
            {
                "id": "100029006250818",
                "count": 0
            },
            {
                "id": "100056087464917",
                "count": 0
            },
            {
                "id": "100071067754623",
                "count": 0
            },
            {
                "id": "100061813050338",
                "count": 0
            },
            {
                "id": "100055836259425",
                "count": 0
            },
            {
                "id": "100023854140281",
                "count": 0
            },
            {
                "id": "100010665249572",
                "count": 0
            },
            {
                "id": "100020878699997",
                "count": 0
            },
            {
                "id": "100047514954366",
                "count": 0
            },
            {
                "id": "100065262047714",
                "count": 0
            },
            {
                "id": "100067243941940",
                "count": 0
            },
            {
                "id": "100067053683911",
                "count": 0
            },
            {
                "id": "100022366803401",
                "count": 0
            },
            {
                "id": "100079666113333",
                "count": 0
            },
            {
                "id": "100073535343306",
                "count": 0
            },
            {
                "id": "100011692905710",
                "count": 0
            },
            {
                "id": "100079453483299",
                "count": 0
            },
            {
                "id": "100007808220730",
                "count": 0
            },
            {
                "id": "100018018068309",
                "count": 0
            },
            {
                "id": "100067031242787",
                "count": 0
            },
            {
                "id": "100066236055494",
                "count": 0
            },
            {
                "id": "100055693593723",
                "count": 0
            },
            {
                "id": "100072701712223",
                "count": 0
            },
            {
                "id": "100065030048161",
                "count": 0
            },
            {
                "id": "100009166856330",
                "count": 0
            },
            {
                "id": "100052746136998",
                "count": 0
            },
            {
                "id": "100014762199928",
                "count": 0
            },
            {
                "id": "100004216305793",
                "count": 0
            },
            {
                "id": "100048984994148",
                "count": 0
            },
            {
                "id": "100012443164409",
                "count": 0
            },
            {
                "id": "100093224341332",
                "count": 0
            },
            {
                "id": "100083380423639",
                "count": 0
            },
            {
                "id": "100016663181910",
                "count": 0
            },
            {
                "id": "100059137774371",
                "count": 0
            },
            {
                "id": "100011467808949",
                "count": 0
            },
            {
                "id": "100034707022479",
                "count": 0
            },
            {
                "id": "100022702847197",
                "count": 0
            },
            {
                "id": "100064057458621",
                "count": 0
            },
            {
                "id": "100003705008879",
                "count": 0
            },
            {
                "id": "100065602475816",
                "count": 0
            },
            {
                "id": "100000154104641",
                "count": 0
            },
            {
                "id": "100085875930262",
                "count": 0
            },
            {
                "id": "100084748442895",
                "count": 0
            },
            {
                "id": "100078329177770",
                "count": 0
            },
            {
                "id": "100062498004609",
                "count": 0
            },
            {
                "id": "100013965996688",
                "count": 0
            },
            {
                "id": "100004763292113",
                "count": 0
            },
            {
                "id": "100012936126213",
                "count": 0
            },
            {
                "id": "100014483565503",
                "count": 0
            },
            {
                "id": "100060277764031",
                "count": 0
            },
            {
                "id": "100017700078094",
                "count": 0
            },
            {
                "id": "100078289572599",
                "count": 0
            },
            {
                "id": "100052712120430",
                "count": 0
            },
            {
                "id": "100039250569229",
                "count": 0
            },
            {
                "id": "100079492153938",
                "count": 0
            }
        ],
        "week": [
            {
                "id": "100074749290620",
                "count": 0
            },
            {
                "id": "100023416734135",
                "count": 0
            },
            {
                "id": "100027948137517",
                "count": 0
            },
            {
                "id": "100029006250818",
                "count": 0
            },
            {
                "id": "100056087464917",
                "count": 0
            },
            {
                "id": "100071067754623",
                "count": 0
            },
            {
                "id": "100061813050338",
                "count": 0
            },
            {
                "id": "100055836259425",
                "count": 0
            },
            {
                "id": "100023854140281",
                "count": 0
            },
            {
                "id": "100010665249572",
                "count": 0
            },
            {
                "id": "100020878699997",
                "count": 0
            },
            {
                "id": "100047514954366",
                "count": 0
            },
            {
                "id": "100065262047714",
                "count": 0
            },
            {
                "id": "100067243941940",
                "count": 0
            },
            {
                "id": "100067053683911",
                "count": 0
            },
            {
                "id": "100022366803401",
                "count": 0
            },
            {
                "id": "100079666113333",
                "count": 0
            },
            {
                "id": "100073535343306",
                "count": 0
            },
            {
                "id": "100011692905710",
                "count": 0
            },
            {
                "id": "100079453483299",
                "count": 0
            },
            {
                "id": "100007808220730",
                "count": 0
            },
            {
                "id": "100018018068309",
                "count": 0
            },
            {
                "id": "100067031242787",
                "count": 0
            },
            {
                "id": "100066236055494",
                "count": 0
            },
            {
                "id": "100055693593723",
                "count": 0
            },
            {
                "id": "100072701712223",
                "count": 0
            },
            {
                "id": "100065030048161",
                "count": 0
            },
            {
                "id": "100009166856330",
                "count": 0
            },
            {
                "id": "100052746136998",
                "count": 0
            },
            {
                "id": "100014762199928",
                "count": 0
            },
            {
                "id": "100004216305793",
                "count": 0
            },
            {
                "id": "100048984994148",
                "count": 0
            },
            {
                "id": "100012443164409",
                "count": 0
            },
            {
                "id": "100093224341332",
                "count": 0
            },
            {
                "id": "100083380423639",
                "count": 0
            },
            {
                "id": "100016663181910",
                "count": 0
            },
            {
                "id": "100059137774371",
                "count": 0
            },
            {
                "id": "100011467808949",
                "count": 0
            },
            {
                "id": "100034707022479",
                "count": 0
            },
            {
                "id": "100022702847197",
                "count": 0
            },
            {
                "id": "100064057458621",
                "count": 0
            },
            {
                "id": "100003705008879",
                "count": 0
            },
            {
                "id": "100065602475816",
                "count": 0
            },
            {
                "id": "100000154104641",
                "count": 0
            },
            {
                "id": "100085875930262",
                "count": 0
            },
            {
                "id": "100084748442895",
                "count": 0
            },
            {
                "id": "100078329177770",
                "count": 0
            },
            {
                "id": "100062498004609",
                "count": 0
            },
            {
                "id": "100013965996688",
                "count": 0
            },
            {
                "id": "100004763292113",
                "count": 0
            },
            {
                "id": "100012936126213",
                "count": 0
            },
            {
                "id": "100014483565503",
                "count": 0
            },
            {
                "id": "100060277764031",
                "count": 0
            },
            {
                "id": "100017700078094",
                "count": 0
            },
            {
                "id": "100078289572599",
                "count": 0
            },
            {
                "id": "100052712120430",
                "count": 0
            },
            {
                "id": "100039250569229",
                "count": 0
            },
            {
                "id": "100079492153938",
                "count": 0
            }
        ]
    }
}