{
    "total": [
        {
            "id": "100089900198076",
            "count": 0
        },
        {
            "id": "100088387453692",
            "count": 0
        },
        {
            "id": "100084974695350",
            "count": 29
        },
        {
            "id": "100089051024561",
            "count": 0
        },
        {
            "id": "100082757734125",
            "count": 15
        },
        {
            "id": "100083403272875",
            "count": 0
        },
        {
            "id": "100049665841261",
            "count": 0
        },
        {
            "id": "100071989926316",
            "count": 0
        },
        {
            "id": "100076723485834",
            "count": 0
        },
        {
            "id": "100080057559630",
            "count": 0
        },
        {
            "id": "100049483279010",
            "count": 0
        },
        {
            "id": "100079339185366",
            "count": 0
        },
        {
            "id": "100088105106234",
            "count": 0
        },
        {
            "id": "100069884408355",
            "count": 0
        },
        {
            "id": "100069721952857",
            "count": 0
        },
        {
            "id": "100078203812128",
            "count": 0
        },
        {
            "id": "100064290794752",
            "count": 10
        },
        {
            "id": "100089142707697",
            "count": 0
        },
        {
            "id": "100087472691247",
            "count": 0
        },
        {
            "id": "100090463925711",
            "count": 0
        },
        {
            "id": "100072626520782",
            "count": 0
        },
        {
            "id": "100088897866138",
            "count": 0
        },
        {
            "id": "100085277637272",
            "count": 0
        },
        {
            "id": "100077413116100",
            "count": 1
        },
        {
            "id": "100085338655381",
            "count": 0
        },
        {
            "id": "100068869418408",
            "count": 0
        },
        {
            "id": "100087627760962",
            "count": 0
        },
        {
            "id": "100079584385613",
            "count": 0
        },
        {
            "id": "100080346820033",
            "count": 0
        },
        {
            "id": "100090466055683",
            "count": 0
        },
        {
            "id": "100062234943643",
            "count": 0
        },
        {
            "id": "100088386355643",
            "count": 0
        },
        {
            "id": "100041785022681",
            "count": 0
        },
        {
            "id": "100064678454248",
            "count": 6
        },
        {
            "id": "100094114306652",
            "count": 0
        },
        {
            "id": "61550326203131",
            "count": 3
        },
        {
            "id": "100041390349328",
            "count": 0
        },
        {
            "id": "100062498004609",
            "count": 31
        }
    ],
    "week": [
        {
            "id": "100089900198076",
            "count": 0
        },
        {
            "id": "100088387453692",
            "count": 0
        },
        {
            "id": "100084974695350",
            "count": 29
        },
        {
            "id": "100089051024561",
            "count": 0
        },
        {
            "id": "100082757734125",
            "count": 15
        },
        {
            "id": "100083403272875",
            "count": 0
        },
        {
            "id": "100049665841261",
            "count": 0
        },
        {
            "id": "100071989926316",
            "count": 0
        },
        {
            "id": "100076723485834",
            "count": 0
        },
        {
            "id": "100080057559630",
            "count": 0
        },
        {
            "id": "100049483279010",
            "count": 0
        },
        {
            "id": "100079339185366",
            "count": 0
        },
        {
            "id": "100088105106234",
            "count": 0
        },
        {
            "id": "100069884408355",
            "count": 0
        },
        {
            "id": "100069721952857",
            "count": 0
        },
        {
            "id": "100078203812128",
            "count": 0
        },
        {
            "id": "100064290794752",
            "count": 10
        },
        {
            "id": "100089142707697",
            "count": 0
        },
        {
            "id": "100087472691247",
            "count": 0
        },
        {
            "id": "100090463925711",
            "count": 0
        },
        {
            "id": "100072626520782",
            "count": 0
        },
        {
            "id": "100088897866138",
            "count": 0
        },
        {
            "id": "100085277637272",
            "count": 0
        },
        {
            "id": "100077413116100",
            "count": 1
        },
        {
            "id": "100085338655381",
            "count": 0
        },
        {
            "id": "100068869418408",
            "count": 0
        },
        {
            "id": "100087627760962",
            "count": 0
        },
        {
            "id": "100079584385613",
            "count": 0
        },
        {
            "id": "100080346820033",
            "count": 0
        },
        {
            "id": "100090466055683",
            "count": 0
        },
        {
            "id": "100062234943643",
            "count": 0
        },
        {
            "id": "100088386355643",
            "count": 0
        },
        {
            "id": "100041785022681",
            "count": 0
        },
        {
            "id": "100064678454248",
            "count": 6
        },
        {
            "id": "100094114306652",
            "count": 0
        },
        {
            "id": "61550326203131",
            "count": 3
        },
        {
            "id": "100041390349328",
            "count": 0
        },
        {
            "id": "100062498004609",
            "count": 31
        }
    ],
    "day": [
        {
            "id": "100089900198076",
            "count": 0
        },
        {
            "id": "100088387453692",
            "count": 0
        },
        {
            "id": "100084974695350",
            "count": 29
        },
        {
            "id": "100089051024561",
            "count": 0
        },
        {
            "id": "100082757734125",
            "count": 15
        },
        {
            "id": "100083403272875",
            "count": 0
        },
        {
            "id": "100049665841261",
            "count": 0
        },
        {
            "id": "100071989926316",
            "count": 0
        },
        {
            "id": "100076723485834",
            "count": 0
        },
        {
            "id": "100080057559630",
            "count": 0
        },
        {
            "id": "100049483279010",
            "count": 0
        },
        {
            "id": "100079339185366",
            "count": 0
        },
        {
            "id": "100088105106234",
            "count": 0
        },
        {
            "id": "100069884408355",
            "count": 0
        },
        {
            "id": "100069721952857",
            "count": 0
        },
        {
            "id": "100078203812128",
            "count": 0
        },
        {
            "id": "100064290794752",
            "count": 10
        },
        {
            "id": "100089142707697",
            "count": 0
        },
        {
            "id": "100087472691247",
            "count": 0
        },
        {
            "id": "100090463925711",
            "count": 0
        },
        {
            "id": "100072626520782",
            "count": 0
        },
        {
            "id": "100088897866138",
            "count": 0
        },
        {
            "id": "100085277637272",
            "count": 0
        },
        {
            "id": "100077413116100",
            "count": 1
        },
        {
            "id": "100085338655381",
            "count": 0
        },
        {
            "id": "100068869418408",
            "count": 0
        },
        {
            "id": "100087627760962",
            "count": 0
        },
        {
            "id": "100079584385613",
            "count": 0
        },
        {
            "id": "100080346820033",
            "count": 0
        },
        {
            "id": "100090466055683",
            "count": 0
        },
        {
            "id": "100062234943643",
            "count": 0
        },
        {
            "id": "100088386355643",
            "count": 0
        },
        {
            "id": "100041785022681",
            "count": 0
        },
        {
            "id": "100064678454248",
            "count": 6
        },
        {
            "id": "100094114306652",
            "count": 0
        },
        {
            "id": "61550326203131",
            "count": 3
        },
        {
            "id": "100041390349328",
            "count": 0
        },
        {
            "id": "100062498004609",
            "count": 31
        }
    ],
    "time": 2,
    "last": {
        "time": 5,
        "day": [
            {
                "id": "100089900198076",
                "count": 0
            },
            {
                "id": "100088387453692",
                "count": 0
            },
            {
                "id": "100084974695350",
                "count": 0
            },
            {
                "id": "100089051024561",
                "count": 0
            },
            {
                "id": "100082757734125",
                "count": 0
            },
            {
                "id": "100083403272875",
                "count": 0
            },
            {
                "id": "100049665841261",
                "count": 0
            },
            {
                "id": "100071989926316",
                "count": 0
            },
            {
                "id": "100076723485834",
                "count": 0
            },
            {
                "id": "100080057559630",
                "count": 0
            },
            {
                "id": "100049483279010",
                "count": 0
            },
            {
                "id": "100079339185366",
                "count": 0
            },
            {
                "id": "100088105106234",
                "count": 0
            },
            {
                "id": "100069884408355",
                "count": 0
            },
            {
                "id": "100069721952857",
                "count": 0
            },
            {
                "id": "100078203812128",
                "count": 0
            },
            {
                "id": "100064290794752",
                "count": 0
            },
            {
                "id": "100089142707697",
                "count": 0
            },
            {
                "id": "100087472691247",
                "count": 0
            },
            {
                "id": "100090463925711",
                "count": 0
            },
            {
                "id": "100072626520782",
                "count": 0
            },
            {
                "id": "100088897866138",
                "count": 0
            },
            {
                "id": "100085277637272",
                "count": 0
            },
            {
                "id": "100077413116100",
                "count": 0
            },
            {
                "id": "100085338655381",
                "count": 0
            },
            {
                "id": "100068869418408",
                "count": 0
            },
            {
                "id": "100087627760962",
                "count": 0
            },
            {
                "id": "100079584385613",
                "count": 0
            },
            {
                "id": "100080346820033",
                "count": 0
            },
            {
                "id": "100090466055683",
                "count": 0
            },
            {
                "id": "100062234943643",
                "count": 0
            },
            {
                "id": "100088386355643",
                "count": 0
            },
            {
                "id": "100041785022681",
                "count": 0
            },
            {
                "id": "100064678454248",
                "count": 0
            },
            {
                "id": "100094114306652",
                "count": 0
            },
            {
                "id": "61550326203131",
                "count": 0
            },
            {
                "id": "100088190829044",
                "count": 0
            },
            {
                "id": "100041390349328",
                "count": 0
            },
            {
                "id": "100062498004609",
                "count": 0
            }
        ],
        "week": [
            {
                "id": "100089900198076",
                "count": 0
            },
            {
                "id": "100088387453692",
                "count": 0
            },
            {
                "id": "100084974695350",
                "count": 0
            },
            {
                "id": "100089051024561",
                "count": 0
            },
            {
                "id": "100082757734125",
                "count": 0
            },
            {
                "id": "100083403272875",
                "count": 0
            },
            {
                "id": "100049665841261",
                "count": 0
            },
            {
                "id": "100071989926316",
                "count": 0
            },
            {
                "id": "100076723485834",
                "count": 0
            },
            {
                "id": "100080057559630",
                "count": 0
            },
            {
                "id": "100049483279010",
                "count": 0
            },
            {
                "id": "100079339185366",
                "count": 0
            },
            {
                "id": "100088105106234",
                "count": 0
            },
            {
                "id": "100069884408355",
                "count": 0
            },
            {
                "id": "100069721952857",
                "count": 0
            },
            {
                "id": "100078203812128",
                "count": 0
            },
            {
                "id": "100064290794752",
                "count": 0
            },
            {
                "id": "100089142707697",
                "count": 0
            },
            {
                "id": "100087472691247",
                "count": 0
            },
            {
                "id": "100090463925711",
                "count": 0
            },
            {
                "id": "100072626520782",
                "count": 0
            },
            {
                "id": "100088897866138",
                "count": 0
            },
            {
                "id": "100085277637272",
                "count": 0
            },
            {
                "id": "100077413116100",
                "count": 0
            },
            {
                "id": "100085338655381",
                "count": 0
            },
            {
                "id": "100068869418408",
                "count": 0
            },
            {
                "id": "100087627760962",
                "count": 0
            },
            {
                "id": "100079584385613",
                "count": 0
            },
            {
                "id": "100080346820033",
                "count": 0
            },
            {
                "id": "100090466055683",
                "count": 0
            },
            {
                "id": "100062234943643",
                "count": 0
            },
            {
                "id": "100088386355643",
                "count": 0
            },
            {
                "id": "100041785022681",
                "count": 0
            },
            {
                "id": "100064678454248",
                "count": 0
            },
            {
                "id": "100094114306652",
                "count": 0
            },
            {
                "id": "61550326203131",
                "count": 0
            },
            {
                "id": "100088190829044",
                "count": 0
            },
            {
                "id": "100041390349328",
                "count": 0
            },
            {
                "id": "100062498004609",
                "count": 0
            }
        ]
    }
}