{
    "total": [
        {
            "id": "100052963966592",
            "count": 13
        },
        {
            "id": "100081489572370",
            "count": 0
        },
        {
            "id": "100032739829671",
            "count": 0
        },
        {
            "id": "100074417089178",
            "count": 0
        },
        {
            "id": "100058079891335",
            "count": 0
        },
        {
            "id": "100078319883153",
            "count": 1330
        },
        {
            "id": "100088539450004",
            "count": 0
        },
        {
            "id": "100091327688860",
            "count": 0
        },
        {
            "id": "100088077541601",
            "count": 0
        },
        {
            "id": "100084793727667",
            "count": 0
        },
        {
            "id": "100019170762275",
            "count": 0
        },
        {
            "id": "100083539161828",
            "count": 0
        },
        {
            "id": "100093021349918",
            "count": 0
        },
        {
            "id": "100091953376581",
            "count": 0
        },
        {
            "id": "100084177841974",
            "count": 1
        },
        {
            "id": "100091187539875",
            "count": 15
        },
        {
            "id": "100084863989584",
            "count": 0
        },
        {
            "id": "100076295198797",
            "count": 0
        },
        {
            "id": "100086556974272",
            "count": 1
        },
        {
            "id": "100093536379171",
            "count": 0
        },
        {
            "id": "100075924261209",
            "count": 1
        },
        {
            "id": "100071917115959",
            "count": 1
        },
        {
            "id": "100070642577090",
            "count": 0
        },
        {
            "id": "100017224539647",
            "count": 0
        },
        {
            "id": "100092696417994",
            "count": 0
        },
        {
            "id": "1290568214",
            "count": 0
        },
        {
            "id": "100079636726683",
            "count": 611
        },
        {
            "id": "100053680880065",
            "count": 0
        },
        {
            "id": "100000815392518",
            "count": 19
        },
        {
            "id": "100083899056120",
            "count": 0
        },
        {
            "id": "100020573657413",
            "count": 0
        },
        {
            "id": "100087646164444",
            "count": 2
        },
        {
            "id": "100046175290266",
            "count": 0
        },
        {
            "id": "100079166545702",
            "count": 0
        },
        {
            "id": "100094951704736",
            "count": 0
        },
        {
            "id": "100040769793012",
            "count": 0
        },
        {
            "id": "100095067551652",
            "count": 1
        },
        {
            "id": "100095270708888",
            "count": 2
        },
        {
            "id": "100056123840391",
            "count": 1
        },
        {
            "id": "100043570995943",
            "count": 2
        },
        {
            "id": "100083139196049",
            "count": 1
        },
        {
            "id": "100092259733661",
            "count": 98
        },
        {
            "id": "100092354074832",
            "count": 0
        },
        {
            "id": "100090108247656",
            "count": 0
        },
        {
            "id": "100089329814892",
            "count": 0
        },
        {
            "id": "100088815633595",
            "count": 0
        },
        {
            "id": "100088460304437",
            "count": 0
        },
        {
            "id": "100085962321791",
            "count": 0
        },
        {
            "id": "100085449626839",
            "count": 0
        },
        {
            "id": "100083972081816",
            "count": 0
        },
        {
            "id": "100082557519890",
            "count": 0
        },
        {
            "id": "100081098426867",
            "count": 0
        },
        {
            "id": "100080694761281",
            "count": 0
        },
        {
            "id": "100079559754792",
            "count": 0
        },
        {
            "id": "100075207703262",
            "count": 0
        },
        {
            "id": "100075043785195",
            "count": 0
        },
        {
            "id": "100073829466797",
            "count": 0
        },
        {
            "id": "100069830462150",
            "count": 0
        },
        {
            "id": "100069002424822",
            "count": 0
        },
        {
            "id": "100056726456140",
            "count": 0
        },
        {
            "id": "100053121562150",
            "count": 0
        },
        {
            "id": "100036903708738",
            "count": 0
        },
        {
            "id": "100015029704051",
            "count": 0
        },
        {
            "id": "100006616082582",
            "count": 0
        },
        {
            "id": "100086741948829",
            "count": 0
        },
        {
            "id": "100093978716465",
            "count": 0
        },
        {
            "id": "100093669915269",
            "count": 0
        },
        {
            "id": "100092958470192",
            "count": 0
        },
        {
            "id": "100092613125561",
            "count": 0
        },
        {
            "id": "100092496723057",
            "count": 0
        },
        {
            "id": "100091943528180",
            "count": 0
        },
        {
            "id": "100091751534109",
            "count": 0
        },
        {
            "id": "100090748661244",
            "count": 0
        },
        {
            "id": "100090565334151",
            "count": 0
        },
        {
            "id": "100090471841612",
            "count": 0
        },
        {
            "id": "100090443620321",
            "count": 0
        },
        {
            "id": "100090109077884",
            "count": 1
        },
        {
            "id": "100089599266669",
            "count": 0
        },
        {
            "id": "100087461693921",
            "count": 0
        },
        {
            "id": "100087284504298",
            "count": 0
        },
        {
            "id": "100086391231336",
            "count": 0
        },
        {
            "id": "100085717096116",
            "count": 0
        },
        {
            "id": "100082615003653",
            "count": 0
        },
        {
            "id": "100081589202800",
            "count": 0
        },
        {
            "id": "100073551865768",
            "count": 0
        },
        {
            "id": "100063661416414",
            "count": 0
        },
        {
            "id": "100062024351877",
            "count": 0
        },
        {
            "id": "100061161195173",
            "count": 0
        },
        {
            "id": "100060182936818",
            "count": 0
        },
        {
            "id": "100055644035937",
            "count": 0
        },
        {
            "id": "100053853640375",
            "count": 0
        },
        {
            "id": "100014723445704",
            "count": 0
        },
        {
            "id": "100079896527459",
            "count": 486
        },
        {
            "id": "100062498004609",
            "count": 1838
        },
        {
            "id": "100092267790910",
            "count": 0
        },
        {
            "id": "100085827969998",
            "count": 0
        },
        {
            "id": "100085027761960",
            "count": 0
        },
        {
            "id": "100082208232579",
            "count": 0
        },
        {
            "id": "100080781242822",
            "count": 0
        },
        {
            "id": "100077031296147",
            "count": 0
        },
        {
            "id": "100066784927356",
            "count": 0
        },
        {
            "id": "100064816184832",
            "count": 0
        },
        {
            "id": "100064453494623",
            "count": 0
        },
        {
            "id": "100062600032403",
            "count": 0
        },
        {
            "id": "100079491357756",
            "count": 39
        },
        {
            "id": "100086058146494",
            "count": 0
        },
        {
            "id": "100090957069531",
            "count": 0
        },
        {
            "id": "100074684310830",
            "count": 10
        },
        {
            "id": "100088221588065",
            "count": 6
        },
        {
            "id": "100073814197811",
            "count": 0
        },
        {
            "id": "100075090636420",
            "count": 0
        },
        {
            "id": "100070294372233",
            "count": 0
        },
        {
            "id": "100089253018008",
            "count": 0
        },
        {
            "id": "100091839446037",
            "count": 16
        },
        {
            "id": "100079492153938",
            "count": 26
        },
        {
            "id": "100094174131962",
            "count": 55
        },
        {
            "id": "100092658575491",
            "count": 0
        },
        {
            "id": "100006587208875",
            "count": 0
        },
        {
            "id": "100089624779513",
            "count": 30
        },
        {
            "id": "100087007603751",
            "count": 0
        }
    ],
    "week": [
        {
            "id": "100052963966592",
            "count": 13
        },
        {
            "id": "100081489572370",
            "count": 0
        },
        {
            "id": "100032739829671",
            "count": 0
        },
        {
            "id": "100074417089178",
            "count": 0
        },
        {
            "id": "100058079891335",
            "count": 0
        },
        {
            "id": "100078319883153",
            "count": 1330
        },
        {
            "id": "100088539450004",
            "count": 0
        },
        {
            "id": "100091327688860",
            "count": 0
        },
        {
            "id": "100088077541601",
            "count": 0
        },
        {
            "id": "100084793727667",
            "count": 0
        },
        {
            "id": "100019170762275",
            "count": 0
        },
        {
            "id": "100083539161828",
            "count": 0
        },
        {
            "id": "100093021349918",
            "count": 0
        },
        {
            "id": "100091953376581",
            "count": 0
        },
        {
            "id": "100084177841974",
            "count": 1
        },
        {
            "id": "100091187539875",
            "count": 15
        },
        {
            "id": "100084863989584",
            "count": 0
        },
        {
            "id": "100076295198797",
            "count": 0
        },
        {
            "id": "100086556974272",
            "count": 1
        },
        {
            "id": "100093536379171",
            "count": 0
        },
        {
            "id": "100075924261209",
            "count": 1
        },
        {
            "id": "100071917115959",
            "count": 1
        },
        {
            "id": "100070642577090",
            "count": 0
        },
        {
            "id": "100017224539647",
            "count": 0
        },
        {
            "id": "100092696417994",
            "count": 0
        },
        {
            "id": "1290568214",
            "count": 0
        },
        {
            "id": "100079636726683",
            "count": 611
        },
        {
            "id": "100053680880065",
            "count": 0
        },
        {
            "id": "100000815392518",
            "count": 19
        },
        {
            "id": "100083899056120",
            "count": 0
        },
        {
            "id": "100020573657413",
            "count": 0
        },
        {
            "id": "100087646164444",
            "count": 2
        },
        {
            "id": "100046175290266",
            "count": 0
        },
        {
            "id": "100079166545702",
            "count": 0
        },
        {
            "id": "100094951704736",
            "count": 0
        },
        {
            "id": "100040769793012",
            "count": 0
        },
        {
            "id": "100095067551652",
            "count": 1
        },
        {
            "id": "100095270708888",
            "count": 2
        },
        {
            "id": "100056123840391",
            "count": 1
        },
        {
            "id": "100043570995943",
            "count": 2
        },
        {
            "id": "100083139196049",
            "count": 1
        },
        {
            "id": "100092259733661",
            "count": 98
        },
        {
            "id": "100092354074832",
            "count": 0
        },
        {
            "id": "100090108247656",
            "count": 0
        },
        {
            "id": "100089329814892",
            "count": 0
        },
        {
            "id": "100088815633595",
            "count": 0
        },
        {
            "id": "100088460304437",
            "count": 0
        },
        {
            "id": "100085962321791",
            "count": 0
        },
        {
            "id": "100085449626839",
            "count": 0
        },
        {
            "id": "100083972081816",
            "count": 0
        },
        {
            "id": "100082557519890",
            "count": 0
        },
        {
            "id": "100081098426867",
            "count": 0
        },
        {
            "id": "100080694761281",
            "count": 0
        },
        {
            "id": "100079559754792",
            "count": 0
        },
        {
            "id": "100075207703262",
            "count": 0
        },
        {
            "id": "100075043785195",
            "count": 0
        },
        {
            "id": "100073829466797",
            "count": 0
        },
        {
            "id": "100069830462150",
            "count": 0
        },
        {
            "id": "100069002424822",
            "count": 0
        },
        {
            "id": "100056726456140",
            "count": 0
        },
        {
            "id": "100053121562150",
            "count": 0
        },
        {
            "id": "100036903708738",
            "count": 0
        },
        {
            "id": "100015029704051",
            "count": 0
        },
        {
            "id": "100006616082582",
            "count": 0
        },
        {
            "id": "100086741948829",
            "count": 0
        },
        {
            "id": "100093978716465",
            "count": 0
        },
        {
            "id": "100093669915269",
            "count": 0
        },
        {
            "id": "100092958470192",
            "count": 0
        },
        {
            "id": "100092613125561",
            "count": 0
        },
        {
            "id": "100092496723057",
            "count": 0
        },
        {
            "id": "100091943528180",
            "count": 0
        },
        {
            "id": "100091751534109",
            "count": 0
        },
        {
            "id": "100090748661244",
            "count": 0
        },
        {
            "id": "100090565334151",
            "count": 0
        },
        {
            "id": "100090471841612",
            "count": 0
        },
        {
            "id": "100090443620321",
            "count": 0
        },
        {
            "id": "100090109077884",
            "count": 1
        },
        {
            "id": "100089599266669",
            "count": 0
        },
        {
            "id": "100087461693921",
            "count": 0
        },
        {
            "id": "100087284504298",
            "count": 0
        },
        {
            "id": "100086391231336",
            "count": 0
        },
        {
            "id": "100085717096116",
            "count": 0
        },
        {
            "id": "100082615003653",
            "count": 0
        },
        {
            "id": "100081589202800",
            "count": 0
        },
        {
            "id": "100073551865768",
            "count": 0
        },
        {
            "id": "100063661416414",
            "count": 0
        },
        {
            "id": "100062024351877",
            "count": 0
        },
        {
            "id": "100061161195173",
            "count": 0
        },
        {
            "id": "100060182936818",
            "count": 0
        },
        {
            "id": "100055644035937",
            "count": 0
        },
        {
            "id": "100053853640375",
            "count": 0
        },
        {
            "id": "100014723445704",
            "count": 0
        },
        {
            "id": "100079896527459",
            "count": 486
        },
        {
            "id": "100062498004609",
            "count": 1838
        },
        {
            "id": "100092267790910",
            "count": 0
        },
        {
            "id": "100085827969998",
            "count": 0
        },
        {
            "id": "100085027761960",
            "count": 0
        },
        {
            "id": "100082208232579",
            "count": 0
        },
        {
            "id": "100080781242822",
            "count": 0
        },
        {
            "id": "100077031296147",
            "count": 0
        },
        {
            "id": "100066784927356",
            "count": 0
        },
        {
            "id": "100064816184832",
            "count": 0
        },
        {
            "id": "100064453494623",
            "count": 0
        },
        {
            "id": "100062600032403",
            "count": 0
        },
        {
            "id": "100079491357756",
            "count": 39
        },
        {
            "id": "100086058146494",
            "count": 0
        },
        {
            "id": "100090957069531",
            "count": 0
        },
        {
            "id": "100074684310830",
            "count": 10
        },
        {
            "id": "100088221588065",
            "count": 6
        },
        {
            "id": "100073814197811",
            "count": 0
        },
        {
            "id": "100075090636420",
            "count": 0
        },
        {
            "id": "100070294372233",
            "count": 0
        },
        {
            "id": "100089253018008",
            "count": 0
        },
        {
            "id": "100091839446037",
            "count": 16
        },
        {
            "id": "100079492153938",
            "count": 26
        },
        {
            "id": "100094174131962",
            "count": 55
        },
        {
            "id": "100092658575491",
            "count": 0
        },
        {
            "id": "100006587208875",
            "count": 0
        },
        {
            "id": "100089624779513",
            "count": 30
        },
        {
            "id": "100087007603751",
            "count": 0
        }
    ],
    "day": [
        {
            "id": "100052963966592",
            "count": 13
        },
        {
            "id": "100081489572370",
            "count": 0
        },
        {
            "id": "100032739829671",
            "count": 0
        },
        {
            "id": "100074417089178",
            "count": 0
        },
        {
            "id": "100058079891335",
            "count": 0
        },
        {
            "id": "100078319883153",
            "count": 1330
        },
        {
            "id": "100088539450004",
            "count": 0
        },
        {
            "id": "100091327688860",
            "count": 0
        },
        {
            "id": "100088077541601",
            "count": 0
        },
        {
            "id": "100084793727667",
            "count": 0
        },
        {
            "id": "100019170762275",
            "count": 0
        },
        {
            "id": "100083539161828",
            "count": 0
        },
        {
            "id": "100093021349918",
            "count": 0
        },
        {
            "id": "100091953376581",
            "count": 0
        },
        {
            "id": "100084177841974",
            "count": 1
        },
        {
            "id": "100091187539875",
            "count": 15
        },
        {
            "id": "100084863989584",
            "count": 0
        },
        {
            "id": "100076295198797",
            "count": 0
        },
        {
            "id": "100086556974272",
            "count": 1
        },
        {
            "id": "100093536379171",
            "count": 0
        },
        {
            "id": "100075924261209",
            "count": 1
        },
        {
            "id": "100071917115959",
            "count": 1
        },
        {
            "id": "100070642577090",
            "count": 0
        },
        {
            "id": "100017224539647",
            "count": 0
        },
        {
            "id": "100092696417994",
            "count": 0
        },
        {
            "id": "1290568214",
            "count": 0
        },
        {
            "id": "100079636726683",
            "count": 611
        },
        {
            "id": "100053680880065",
            "count": 0
        },
        {
            "id": "100000815392518",
            "count": 19
        },
        {
            "id": "100083899056120",
            "count": 0
        },
        {
            "id": "100020573657413",
            "count": 0
        },
        {
            "id": "100087646164444",
            "count": 2
        },
        {
            "id": "100046175290266",
            "count": 0
        },
        {
            "id": "100079166545702",
            "count": 0
        },
        {
            "id": "100094951704736",
            "count": 0
        },
        {
            "id": "100040769793012",
            "count": 0
        },
        {
            "id": "100095067551652",
            "count": 1
        },
        {
            "id": "100095270708888",
            "count": 2
        },
        {
            "id": "100056123840391",
            "count": 1
        },
        {
            "id": "100043570995943",
            "count": 2
        },
        {
            "id": "100083139196049",
            "count": 1
        },
        {
            "id": "100092259733661",
            "count": 98
        },
        {
            "id": "100092354074832",
            "count": 0
        },
        {
            "id": "100090108247656",
            "count": 0
        },
        {
            "id": "100089329814892",
            "count": 0
        },
        {
            "id": "100088815633595",
            "count": 0
        },
        {
            "id": "100088460304437",
            "count": 0
        },
        {
            "id": "100085962321791",
            "count": 0
        },
        {
            "id": "100085449626839",
            "count": 0
        },
        {
            "id": "100083972081816",
            "count": 0
        },
        {
            "id": "100082557519890",
            "count": 0
        },
        {
            "id": "100081098426867",
            "count": 0
        },
        {
            "id": "100080694761281",
            "count": 0
        },
        {
            "id": "100079559754792",
            "count": 0
        },
        {
            "id": "100075207703262",
            "count": 0
        },
        {
            "id": "100075043785195",
            "count": 0
        },
        {
            "id": "100073829466797",
            "count": 0
        },
        {
            "id": "100069830462150",
            "count": 0
        },
        {
            "id": "100069002424822",
            "count": 0
        },
        {
            "id": "100056726456140",
            "count": 0
        },
        {
            "id": "100053121562150",
            "count": 0
        },
        {
            "id": "100036903708738",
            "count": 0
        },
        {
            "id": "100015029704051",
            "count": 0
        },
        {
            "id": "100006616082582",
            "count": 0
        },
        {
            "id": "100086741948829",
            "count": 0
        },
        {
            "id": "100093978716465",
            "count": 0
        },
        {
            "id": "100093669915269",
            "count": 0
        },
        {
            "id": "100092958470192",
            "count": 0
        },
        {
            "id": "100092613125561",
            "count": 0
        },
        {
            "id": "100092496723057",
            "count": 0
        },
        {
            "id": "100091943528180",
            "count": 0
        },
        {
            "id": "100091751534109",
            "count": 0
        },
        {
            "id": "100090748661244",
            "count": 0
        },
        {
            "id": "100090565334151",
            "count": 0
        },
        {
            "id": "100090471841612",
            "count": 0
        },
        {
            "id": "100090443620321",
            "count": 0
        },
        {
            "id": "100090109077884",
            "count": 1
        },
        {
            "id": "100089599266669",
            "count": 0
        },
        {
            "id": "100087461693921",
            "count": 0
        },
        {
            "id": "100087284504298",
            "count": 0
        },
        {
            "id": "100086391231336",
            "count": 0
        },
        {
            "id": "100085717096116",
            "count": 0
        },
        {
            "id": "100082615003653",
            "count": 0
        },
        {
            "id": "100081589202800",
            "count": 0
        },
        {
            "id": "100073551865768",
            "count": 0
        },
        {
            "id": "100063661416414",
            "count": 0
        },
        {
            "id": "100062024351877",
            "count": 0
        },
        {
            "id": "100061161195173",
            "count": 0
        },
        {
            "id": "100060182936818",
            "count": 0
        },
        {
            "id": "100055644035937",
            "count": 0
        },
        {
            "id": "100053853640375",
            "count": 0
        },
        {
            "id": "100014723445704",
            "count": 0
        },
        {
            "id": "100079896527459",
            "count": 486
        },
        {
            "id": "100062498004609",
            "count": 1838
        },
        {
            "id": "100092267790910",
            "count": 0
        },
        {
            "id": "100085827969998",
            "count": 0
        },
        {
            "id": "100085027761960",
            "count": 0
        },
        {
            "id": "100082208232579",
            "count": 0
        },
        {
            "id": "100080781242822",
            "count": 0
        },
        {
            "id": "100077031296147",
            "count": 0
        },
        {
            "id": "100066784927356",
            "count": 0
        },
        {
            "id": "100064816184832",
            "count": 0
        },
        {
            "id": "100064453494623",
            "count": 0
        },
        {
            "id": "100062600032403",
            "count": 0
        },
        {
            "id": "100079491357756",
            "count": 39
        },
        {
            "id": "100086058146494",
            "count": 0
        },
        {
            "id": "100090957069531",
            "count": 0
        },
        {
            "id": "100074684310830",
            "count": 10
        },
        {
            "id": "100088221588065",
            "count": 6
        },
        {
            "id": "100073814197811",
            "count": 0
        },
        {
            "id": "100075090636420",
            "count": 0
        },
        {
            "id": "100070294372233",
            "count": 0
        },
        {
            "id": "100089253018008",
            "count": 0
        },
        {
            "id": "100091839446037",
            "count": 16
        },
        {
            "id": "100079492153938",
            "count": 26
        },
        {
            "id": "100094174131962",
            "count": 55
        },
        {
            "id": "100092658575491",
            "count": 0
        },
        {
            "id": "100006587208875",
            "count": 0
        },
        {
            "id": "100089624779513",
            "count": 30
        },
        {
            "id": "100087007603751",
            "count": 0
        }
    ],
    "time": 2,
    "last": {
        "time": 0,
        "day": [
            {
                "id": "100052963966592",
                "count": 0
            },
            {
                "id": "100081489572370",
                "count": 0
            },
            {
                "id": "100032739829671",
                "count": 0
            },
            {
                "id": "100074417089178",
                "count": 0
            },
            {
                "id": "100058079891335",
                "count": 0
            },
            {
                "id": "100078319883153",
                "count": 0
            },
            {
                "id": "100088539450004",
                "count": 0
            },
            {
                "id": "100091327688860",
                "count": 0
            },
            {
                "id": "100088077541601",
                "count": 0
            },
            {
                "id": "100084793727667",
                "count": 0
            },
            {
                "id": "100087007603751",
                "count": 0
            },
            {
                "id": "100019170762275",
                "count": 0
            },
            {
                "id": "100083539161828",
                "count": 0
            },
            {
                "id": "100093021349918",
                "count": 0
            },
            {
                "id": "100091953376581",
                "count": 0
            },
            {
                "id": "100084177841974",
                "count": 0
            },
            {
                "id": "100091187539875",
                "count": 0
            },
            {
                "id": "100084863989584",
                "count": 0
            },
            {
                "id": "100076295198797",
                "count": 0
            },
            {
                "id": "100086556974272",
                "count": 0
            },
            {
                "id": "100093536379171",
                "count": 0
            },
            {
                "id": "100063405765704",
                "count": 0
            },
            {
                "id": "100075924261209",
                "count": 0
            },
            {
                "id": "100071917115959",
                "count": 0
            },
            {
                "id": "100070642577090",
                "count": 0
            },
            {
                "id": "100017224539647",
                "count": 0
            },
            {
                "id": "100092696417994",
                "count": 0
            },
            {
                "id": "1290568214",
                "count": 0
            },
            {
                "id": "100079636726683",
                "count": 0
            },
            {
                "id": "100053680880065",
                "count": 0
            },
            {
                "id": "100000815392518",
                "count": 0
            },
            {
                "id": "100083899056120",
                "count": 0
            },
            {
                "id": "100020573657413",
                "count": 0
            },
            {
                "id": "100087646164444",
                "count": 0
            },
            {
                "id": "100046175290266",
                "count": 0
            },
            {
                "id": "100079166545702",
                "count": 0
            },
            {
                "id": "100094951704736",
                "count": 0
            },
            {
                "id": "100040769793012",
                "count": 0
            },
            {
                "id": "100095067551652",
                "count": 0
            },
            {
                "id": "100095270708888",
                "count": 0
            },
            {
                "id": "100056123840391",
                "count": 0
            },
            {
                "id": "100043570995943",
                "count": 0
            },
            {
                "id": "100083139196049",
                "count": 0
            },
            {
                "id": "100092259733661",
                "count": 0
            },
            {
                "id": "100092354074832",
                "count": 0
            },
            {
                "id": "100090108247656",
                "count": 0
            },
            {
                "id": "100089329814892",
                "count": 0
            },
            {
                "id": "100088815633595",
                "count": 0
            },
            {
                "id": "100088460304437",
                "count": 0
            },
            {
                "id": "100085962321791",
                "count": 0
            },
            {
                "id": "100085449626839",
                "count": 0
            },
            {
                "id": "100083972081816",
                "count": 0
            },
            {
                "id": "100082557519890",
                "count": 0
            },
            {
                "id": "100081098426867",
                "count": 0
            },
            {
                "id": "100080694761281",
                "count": 0
            },
            {
                "id": "100079559754792",
                "count": 0
            },
            {
                "id": "100075207703262",
                "count": 0
            },
            {
                "id": "100075043785195",
                "count": 0
            },
            {
                "id": "100073829466797",
                "count": 0
            },
            {
                "id": "100069830462150",
                "count": 0
            },
            {
                "id": "100069002424822",
                "count": 0
            },
            {
                "id": "100056726456140",
                "count": 0
            },
            {
                "id": "100053121562150",
                "count": 0
            },
            {
                "id": "100036903708738",
                "count": 0
            },
            {
                "id": "100015029704051",
                "count": 0
            },
            {
                "id": "100006616082582",
                "count": 0
            },
            {
                "id": "100086741948829",
                "count": 0
            },
            {
                "id": "100093978716465",
                "count": 0
            },
            {
                "id": "100093669915269",
                "count": 0
            },
            {
                "id": "100092958470192",
                "count": 0
            },
            {
                "id": "100092613125561",
                "count": 0
            },
            {
                "id": "100092496723057",
                "count": 0
            },
            {
                "id": "100091943528180",
                "count": 0
            },
            {
                "id": "100091751534109",
                "count": 0
            },
            {
                "id": "100090748661244",
                "count": 0
            },
            {
                "id": "100090565334151",
                "count": 0
            },
            {
                "id": "100090471841612",
                "count": 0
            },
            {
                "id": "100090443620321",
                "count": 0
            },
            {
                "id": "100090109077884",
                "count": 0
            },
            {
                "id": "100089599266669",
                "count": 0
            },
            {
                "id": "100087461693921",
                "count": 0
            },
            {
                "id": "100087284504298",
                "count": 0
            },
            {
                "id": "100086391231336",
                "count": 0
            },
            {
                "id": "100085717096116",
                "count": 0
            },
            {
                "id": "100082615003653",
                "count": 0
            },
            {
                "id": "100081589202800",
                "count": 0
            },
            {
                "id": "100073551865768",
                "count": 0
            },
            {
                "id": "100063661416414",
                "count": 0
            },
            {
                "id": "100062024351877",
                "count": 0
            },
            {
                "id": "100061161195173",
                "count": 0
            },
            {
                "id": "100060182936818",
                "count": 0
            },
            {
                "id": "100055644035937",
                "count": 0
            },
            {
                "id": "100053853640375",
                "count": 0
            },
            {
                "id": "100014723445704",
                "count": 0
            },
            {
                "id": "100079896527459",
                "count": 0
            },
            {
                "id": "100062498004609",
                "count": 0
            },
            {
                "id": "100092267790910",
                "count": 0
            },
            {
                "id": "100085827969998",
                "count": 0
            },
            {
                "id": "100085027761960",
                "count": 0
            },
            {
                "id": "100082208232579",
                "count": 0
            },
            {
                "id": "100080781242822",
                "count": 0
            },
            {
                "id": "100077031296147",
                "count": 0
            },
            {
                "id": "100066784927356",
                "count": 0
            },
            {
                "id": "100064816184832",
                "count": 0
            },
            {
                "id": "100064453494623",
                "count": 0
            },
            {
                "id": "100062600032403",
                "count": 0
            },
            {
                "id": "100071896082963",
                "count": 0
            },
            {
                "id": "100079491357756",
                "count": 0
            },
            {
                "id": "100086058146494",
                "count": 0
            },
            {
                "id": "100090957069531",
                "count": 0
            },
            {
                "id": "100074684310830",
                "count": 0
            },
            {
                "id": "100088221588065",
                "count": 0
            },
            {
                "id": "100073814197811",
                "count": 0
            },
            {
                "id": "100075090636420",
                "count": 0
            },
            {
                "id": "100066935648941",
                "count": 0
            },
            {
                "id": "100079203134612",
                "count": 0
            },
            {
                "id": "100070294372233",
                "count": 0
            },
            {
                "id": "100089253018008",
                "count": 0
            },
            {
                "id": "100091839446037",
                "count": 0
            },
            {
                "id": "100079492153938",
                "count": 0
            },
            {
                "id": "100073633500368",
                "count": 0
            },
            {
                "id": "100094174131962",
                "count": 0
            },
            {
                "id": "100092658575491",
                "count": 0
            },
            {
                "id": "100052623367650",
                "count": 0
            },
            {
                "id": "100004242424242",
                "count": 0
            },
            {
                "id": "100093107906293",
                "count": 0
            },
            {
                "id": "100006587208875",
                "count": 0
            },
            {
                "id": "100089624779513",
                "count": 0
            },
            {
                "id": "100066390524612",
                "count": 0
            }
        ],
        "week": [
            {
                "id": "100052963966592",
                "count": 0
            },
            {
                "id": "100081489572370",
                "count": 0
            },
            {
                "id": "100032739829671",
                "count": 0
            },
            {
                "id": "100074417089178",
                "count": 0
            },
            {
                "id": "100058079891335",
                "count": 0
            },
            {
                "id": "100078319883153",
                "count": 0
            },
            {
                "id": "100088539450004",
                "count": 0
            },
            {
                "id": "100091327688860",
                "count": 0
            },
            {
                "id": "100088077541601",
                "count": 0
            },
            {
                "id": "100084793727667",
                "count": 0
            },
            {
                "id": "100087007603751",
                "count": 0
            },
            {
                "id": "100019170762275",
                "count": 0
            },
            {
                "id": "100083539161828",
                "count": 0
            },
            {
                "id": "100093021349918",
                "count": 0
            },
            {
                "id": "100091953376581",
                "count": 0
            },
            {
                "id": "100084177841974",
                "count": 0
            },
            {
                "id": "100091187539875",
                "count": 0
            },
            {
                "id": "100084863989584",
                "count": 0
            },
            {
                "id": "100076295198797",
                "count": 0
            },
            {
                "id": "100086556974272",
                "count": 0
            },
            {
                "id": "100093536379171",
                "count": 0
            },
            {
                "id": "100063405765704",
                "count": 0
            },
            {
                "id": "100075924261209",
                "count": 0
            },
            {
                "id": "100071917115959",
                "count": 0
            },
            {
                "id": "100070642577090",
                "count": 0
            },
            {
                "id": "100017224539647",
                "count": 0
            },
            {
                "id": "100092696417994",
                "count": 0
            },
            {
                "id": "1290568214",
                "count": 0
            },
            {
                "id": "100079636726683",
                "count": 0
            },
            {
                "id": "100053680880065",
                "count": 0
            },
            {
                "id": "100000815392518",
                "count": 0
            },
            {
                "id": "100083899056120",
                "count": 0
            },
            {
                "id": "100020573657413",
                "count": 0
            },
            {
                "id": "100087646164444",
                "count": 0
            },
            {
                "id": "100046175290266",
                "count": 0
            },
            {
                "id": "100079166545702",
                "count": 0
            },
            {
                "id": "100094951704736",
                "count": 0
            },
            {
                "id": "100040769793012",
                "count": 0
            },
            {
                "id": "100095067551652",
                "count": 0
            },
            {
                "id": "100095270708888",
                "count": 0
            },
            {
                "id": "100056123840391",
                "count": 0
            },
            {
                "id": "100043570995943",
                "count": 0
            },
            {
                "id": "100083139196049",
                "count": 0
            },
            {
                "id": "100092259733661",
                "count": 0
            },
            {
                "id": "100092354074832",
                "count": 0
            },
            {
                "id": "100090108247656",
                "count": 0
            },
            {
                "id": "100089329814892",
                "count": 0
            },
            {
                "id": "100088815633595",
                "count": 0
            },
            {
                "id": "100088460304437",
                "count": 0
            },
            {
                "id": "100085962321791",
                "count": 0
            },
            {
                "id": "100085449626839",
                "count": 0
            },
            {
                "id": "100083972081816",
                "count": 0
            },
            {
                "id": "100082557519890",
                "count": 0
            },
            {
                "id": "100081098426867",
                "count": 0
            },
            {
                "id": "100080694761281",
                "count": 0
            },
            {
                "id": "100079559754792",
                "count": 0
            },
            {
                "id": "100075207703262",
                "count": 0
            },
            {
                "id": "100075043785195",
                "count": 0
            },
            {
                "id": "100073829466797",
                "count": 0
            },
            {
                "id": "100069830462150",
                "count": 0
            },
            {
                "id": "100069002424822",
                "count": 0
            },
            {
                "id": "100056726456140",
                "count": 0
            },
            {
                "id": "100053121562150",
                "count": 0
            },
            {
                "id": "100036903708738",
                "count": 0
            },
            {
                "id": "100015029704051",
                "count": 0
            },
            {
                "id": "100006616082582",
                "count": 0
            },
            {
                "id": "100086741948829",
                "count": 0
            },
            {
                "id": "100093978716465",
                "count": 0
            },
            {
                "id": "100093669915269",
                "count": 0
            },
            {
                "id": "100092958470192",
                "count": 0
            },
            {
                "id": "100092613125561",
                "count": 0
            },
            {
                "id": "100092496723057",
                "count": 0
            },
            {
                "id": "100091943528180",
                "count": 0
            },
            {
                "id": "100091751534109",
                "count": 0
            },
            {
                "id": "100090748661244",
                "count": 0
            },
            {
                "id": "100090565334151",
                "count": 0
            },
            {
                "id": "100090471841612",
                "count": 0
            },
            {
                "id": "100090443620321",
                "count": 0
            },
            {
                "id": "100090109077884",
                "count": 0
            },
            {
                "id": "100089599266669",
                "count": 0
            },
            {
                "id": "100087461693921",
                "count": 0
            },
            {
                "id": "100087284504298",
                "count": 0
            },
            {
                "id": "100086391231336",
                "count": 0
            },
            {
                "id": "100085717096116",
                "count": 0
            },
            {
                "id": "100082615003653",
                "count": 0
            },
            {
                "id": "100081589202800",
                "count": 0
            },
            {
                "id": "100073551865768",
                "count": 0
            },
            {
                "id": "100063661416414",
                "count": 0
            },
            {
                "id": "100062024351877",
                "count": 0
            },
            {
                "id": "100061161195173",
                "count": 0
            },
            {
                "id": "100060182936818",
                "count": 0
            },
            {
                "id": "100055644035937",
                "count": 0
            },
            {
                "id": "100053853640375",
                "count": 0
            },
            {
                "id": "100014723445704",
                "count": 0
            },
            {
                "id": "100079896527459",
                "count": 0
            },
            {
                "id": "100062498004609",
                "count": 0
            },
            {
                "id": "100092267790910",
                "count": 0
            },
            {
                "id": "100085827969998",
                "count": 0
            },
            {
                "id": "100085027761960",
                "count": 0
            },
            {
                "id": "100082208232579",
                "count": 0
            },
            {
                "id": "100080781242822",
                "count": 0
            },
            {
                "id": "100077031296147",
                "count": 0
            },
            {
                "id": "100066784927356",
                "count": 0
            },
            {
                "id": "100064816184832",
                "count": 0
            },
            {
                "id": "100064453494623",
                "count": 0
            },
            {
                "id": "100062600032403",
                "count": 0
            },
            {
                "id": "100071896082963",
                "count": 0
            },
            {
                "id": "100079491357756",
                "count": 0
            },
            {
                "id": "100086058146494",
                "count": 0
            },
            {
                "id": "100090957069531",
                "count": 0
            },
            {
                "id": "100074684310830",
                "count": 0
            },
            {
                "id": "100088221588065",
                "count": 0
            },
            {
                "id": "100073814197811",
                "count": 0
            },
            {
                "id": "100075090636420",
                "count": 0
            },
            {
                "id": "100066935648941",
                "count": 0
            },
            {
                "id": "100079203134612",
                "count": 0
            },
            {
                "id": "100070294372233",
                "count": 0
            },
            {
                "id": "100089253018008",
                "count": 0
            },
            {
                "id": "100091839446037",
                "count": 0
            },
            {
                "id": "100079492153938",
                "count": 0
            },
            {
                "id": "100073633500368",
                "count": 0
            },
            {
                "id": "100094174131962",
                "count": 0
            },
            {
                "id": "100092658575491",
                "count": 0
            },
            {
                "id": "100052623367650",
                "count": 0
            },
            {
                "id": "100004242424242",
                "count": 0
            },
            {
                "id": "100093107906293",
                "count": 0
            },
            {
                "id": "100006587208875",
                "count": 0
            },
            {
                "id": "100089624779513",
                "count": 0
            },
            {
                "id": "100066390524612",
                "count": 0
            }
        ]
    }
}